scilayout/__init__.py
scilayout/base.py
scilayout/classes.py
scilayout/grid.py
scilayout/locations.py
scilayout/scalebars.py
scilayout/stats.py
scilayout/style.py
scilayout/types.py
scilayout-0.1.2.dist-info/licenses/LICENSE
scilayout-0.1.2.dist-info/METADATA
scilayout-0.1.2.dist-info/WHEEL
scilayout-0.1.2.dist-info/top_level.txt
scilayout-0.1.2.dist-info/RECORD
