Metadata-Version: 2.4
Name: scilayout
Version: 0.1.2
Summary: Create axes from top left of figure in centimetres to simplify scientific figure generation.
Author: George Stuyt
License-Expression: GPL-3.0-or-later
Project-URL: Repository, https://github.com/ogeesan/scilayout.git
Project-URL: Issues, https://github.com/ogeesan/scilayout/issues
Keywords: matplotlib-figures,scientific-papers,thesis-template,matplotlib-styles,python
Classifier: Development Status :: 4 - Beta
Classifier: Framework :: Matplotlib
Classifier: Intended Audience :: Science/Research
Classifier: Programming Language :: Python
Classifier: Topic :: Artistic Software
Classifier: Topic :: Multimedia :: Graphics :: Presentation
Classifier: Topic :: Multimedia :: Graphics :: Editors :: Vector-Based
Classifier: Topic :: Scientific/Engineering :: Visualization
Requires-Python: >=3.9
License-File: LICENSE
Requires-Dist: matplotlib
Requires-Dist: numpy
Dynamic: license-file
